<?xml version="1.0" encoding="UTF-8"?>
<!DOCTYPE mapper PUBLIC "-//mybatis.org//DTD Mapper 3.0//EN" "http://mybatis.org/dtd/mybatis-3-mapper.dtd">
<mapper namespace="com.yintu.ruixing.dao.TransformerShouDuanDao">
  <resultMap id="BaseResultMap" type="com.yintu.ruixing.entity.TransformerShouDuanEntity">
    <id column="id" jdbcType="INTEGER" property="id" />
    <result column="xid" jdbcType="INTEGER" property="xid" />
    <result column="cid" jdbcType="INTEGER" property="cid" />
    <result column="mA_Cable_JBP" jdbcType="INTEGER" property="maCableJbp" />
    <result column="A_longIn_JBP" jdbcType="INTEGER" property="aLonginJbp" />
    <result column="A_longOut_JBP" jdbcType="INTEGER" property="aLongoutJbp" />
    <result column="A_shortIn_JBP" jdbcType="INTEGER" property="aShortinJbp" />
    <result column="A_shortOut_JBP" jdbcType="INTEGER" property="aShortoutJbp" />
    <result column="T_JBP" jdbcType="INTEGER" property="tJbp" />
    <result column="yuliu" jdbcType="VARCHAR" property="yuliu" />
    <result column="type" jdbcType="SMALLINT" property="type" />
  </resultMap>
  <sql id="Base_Column_List">
    id, xid, cid, mA_Cable_JBP, A_longIn_JBP, A_longOut_JBP, A_shortIn_JBP, A_shortOut_JBP, 
    T_JBP, yuliu, type
  </sql>
  <select id="selectByPrimaryKey" parameterType="java.lang.Integer" resultMap="BaseResultMap">
    select 
    <include refid="Base_Column_List" />
    from mro_transformer_shouduan
    where id = #{id,jdbcType=INTEGER}
  </select>

  <select id="selectByAll"  resultMap="BaseResultMap">
    select
    <include refid="Base_Column_List" />
    from mro_transformer_shouduan
  </select>
  <select id="selectByCidAndXid" resultMap="BaseResultMap">
    select
    <include refid="Base_Column_List"/>
    from mro_transformer_shouduan
    where cid=#{cid} and
    xid=#{xid}
  </select>
  <delete id="deleteByPrimaryKey" parameterType="java.lang.Integer">
    delete from mro_transformer_shouduan
    where id = #{id,jdbcType=INTEGER}
  </delete>
  <insert id="insert" parameterType="com.yintu.ruixing.entity.TransformerShouDuanEntity">
    insert into mro_transformer_shouduan (id, xid, cid, 
      mA_Cable_JBP, A_longIn_JBP, A_longOut_JBP, 
      A_shortIn_JBP, A_shortOut_JBP, T_JBP, 
      yuliu, type)
    values (#{id,jdbcType=INTEGER}, #{xid,jdbcType=INTEGER}, #{cid,jdbcType=INTEGER}, 
      #{maCableJbp,jdbcType=INTEGER}, #{aLonginJbp,jdbcType=INTEGER}, #{aLongoutJbp,jdbcType=INTEGER}, 
      #{aShortinJbp,jdbcType=INTEGER}, #{aShortoutJbp,jdbcType=INTEGER}, #{tJbp,jdbcType=INTEGER}, 
      #{yuliu,jdbcType=VARCHAR}, #{type,jdbcType=SMALLINT})
  </insert>
  <insert id="insertSelective" parameterType="com.yintu.ruixing.entity.TransformerShouDuanEntity">
    insert into mro_transformer_shouduan
    <trim prefix="(" suffix=")" suffixOverrides=",">
      <if test="id != null">
        id,
      </if>
      <if test="xid != null">
        xid,
      </if>
      <if test="cid != null">
        cid,
      </if>
      <if test="maCableJbp != null">
        mA_Cable_JBP,
      </if>
      <if test="aLonginJbp != null">
        A_longIn_JBP,
      </if>
      <if test="aLongoutJbp != null">
        A_longOut_JBP,
      </if>
      <if test="aShortinJbp != null">
        A_shortIn_JBP,
      </if>
      <if test="aShortoutJbp != null">
        A_shortOut_JBP,
      </if>
      <if test="tJbp != null">
        T_JBP,
      </if>
      <if test="yuliu != null">
        yuliu,
      </if>
      <if test="type != null">
        type,
      </if>
    </trim>
    <trim prefix="values (" suffix=")" suffixOverrides=",">
      <if test="id != null">
        #{id,jdbcType=INTEGER},
      </if>
      <if test="xid != null">
        #{xid,jdbcType=INTEGER},
      </if>
      <if test="cid != null">
        #{cid,jdbcType=INTEGER},
      </if>
      <if test="maCableJbp != null">
        #{maCableJbp,jdbcType=INTEGER},
      </if>
      <if test="aLonginJbp != null">
        #{aLonginJbp,jdbcType=INTEGER},
      </if>
      <if test="aLongoutJbp != null">
        #{aLongoutJbp,jdbcType=INTEGER},
      </if>
      <if test="aShortinJbp != null">
        #{aShortinJbp,jdbcType=INTEGER},
      </if>
      <if test="aShortoutJbp != null">
        #{aShortoutJbp,jdbcType=INTEGER},
      </if>
      <if test="tJbp != null">
        #{tJbp,jdbcType=INTEGER},
      </if>
      <if test="yuliu != null">
        #{yuliu,jdbcType=VARCHAR},
      </if>
      <if test="type != null">
        #{type,jdbcType=SMALLINT},
      </if>
    </trim>
  </insert>
  <update id="updateByPrimaryKeySelective" parameterType="com.yintu.ruixing.entity.TransformerShouDuanEntity">
    update mro_transformer_shouduan
    <set>
      <if test="xid != null">
        xid = #{xid,jdbcType=INTEGER},
      </if>
      <if test="cid != null">
        cid = #{cid,jdbcType=INTEGER},
      </if>
      <if test="maCableJbp != null">
        mA_Cable_JBP = #{maCableJbp,jdbcType=INTEGER},
      </if>
      <if test="aLonginJbp != null">
        A_longIn_JBP = #{aLonginJbp,jdbcType=INTEGER},
      </if>
      <if test="aLongoutJbp != null">
        A_longOut_JBP = #{aLongoutJbp,jdbcType=INTEGER},
      </if>
      <if test="aShortinJbp != null">
        A_shortIn_JBP = #{aShortinJbp,jdbcType=INTEGER},
      </if>
      <if test="aShortoutJbp != null">
        A_shortOut_JBP = #{aShortoutJbp,jdbcType=INTEGER},
      </if>
      <if test="tJbp != null">
        T_JBP = #{tJbp,jdbcType=INTEGER},
      </if>
      <if test="yuliu != null">
        yuliu = #{yuliu,jdbcType=VARCHAR},
      </if>
      <if test="type != null">
        type = #{type,jdbcType=SMALLINT},
      </if>
    </set>
    where id = #{id,jdbcType=INTEGER}
  </update>
  <update id="updateByPrimaryKey" parameterType="com.yintu.ruixing.entity.TransformerShouDuanEntity">
    update mro_transformer_shouduan
    set xid = #{xid,jdbcType=INTEGER},
      cid = #{cid,jdbcType=INTEGER},
      mA_Cable_JBP = #{maCableJbp,jdbcType=INTEGER},
      A_longIn_JBP = #{aLonginJbp,jdbcType=INTEGER},
      A_longOut_JBP = #{aLongoutJbp,jdbcType=INTEGER},
      A_shortIn_JBP = #{aShortinJbp,jdbcType=INTEGER},
      A_shortOut_JBP = #{aShortoutJbp,jdbcType=INTEGER},
      T_JBP = #{tJbp,jdbcType=INTEGER},
      yuliu = #{yuliu,jdbcType=VARCHAR},
      type = #{type,jdbcType=SMALLINT}
    where id = #{id,jdbcType=INTEGER}
  </update>
</mapper>